tortoise-stubs/fields/__init__.pyi
tortoise-stubs/py.typed
tortoise_stubs-0.3.6.dist-info/LICENSE
tortoise_stubs-0.3.6.dist-info/WHEEL
tortoise_stubs-0.3.6.dist-info/METADATA
tortoise_stubs-0.3.6.dist-info/RECORD
