Metadata-Version: 2.1
Name: tortoise-stubs
Version: 0.3.6
Summary: Type stubs that make tortoise-orm a lot easier to work with when using type checkers.
Home-page: https://github.com/Ovsyanka83/tortoise-stubs
License: MIT
Author: Stanislav Zmiev
Author-email: szmiev2000@gmail.com
Requires-Python: >=3.8,<4.0
Classifier: License :: OSI Approved :: MIT License
Classifier: Programming Language :: Python :: 3
Classifier: Programming Language :: Python :: 3.10
Classifier: Programming Language :: Python :: 3.8
Classifier: Programming Language :: Python :: 3.9
Requires-Dist: tortoise-orm
Project-URL: Repository, https://github.com/Ovsyanka83/tortoise-stubs
